{
  "description": "项目配置文件",
  "compileType": "miniprogram",
  "setting": {
    "useCompilerPlugins": [
      "typescript",
      "sass"
    ],
    "babelSetting": {
      "ignore": [],
      "disablePlugins": [],
      "outputPath": ""
    },
    "coverView": false,
    "postcss": false,
    "minified": false,
    "enhance": false,
    "showShadowRootInWxmlPanel": false,
    "packNpmRelationList": [],
    "ignoreUploadUnusedFiles": true,
    "compileHotReLoad": false,
    "skylineRenderEnable": true
  },
  "simulatorType": "wechat",
  "simulatorPluginLibVersion": {},
  "condition": {},
  "editorSetting": {
    "tabIndent": "insertSpaces",
    "tabSize": 2
  },
  "libVersion": "2.32.3",
  "packOptions": {
    "ignore": [],
    "include": []
  },
  "appid": "wxd49a5faadd48e915",
  "projectname": "wechat-miniprogram"
}